my_import/MyBrowser.py
my_import/__init__.py
my_import/auto_control.py
my_import/c_print.py
my_import/check_input.py
my_import/class_builder.py
my_import/convert.py
my_import/custom_importer.py
my_import/file_config.py
my_import/file_processing.py
my_import/hsr_build.py
my_import/hsr_constants.py
my_import/hsr_data_structure.py
my_import/hsr_decorator.py
my_import/hsr_info.py
my_import/hsr_list.py
my_import/hsr_math.py
my_import/hsr_run.py
my_import/performer_helper.py
my_import/private.py
my_import/quick_git.py
my_import/setup_paths.py
my_import/start_server.py
my_import/string_processing.py
my_import/super_analyze.py
my_import/system.py
my_import/update_env.py
my_import/webscraper.py
my_import/window.py
my_import/AI/AI.py
my_import/AI/Build_Datadir.py
my_import/AI/DQN.py
my_import/AI/Diffusion.py
my_import/AI/Excel.py
my_import/AI/FacePerception.py
my_import/AI/Game.py
my_import/AI/MCTS.py
my_import/AI/ML.py
my_import/AI/Metalearning.py
my_import/AI/Minimax.py
my_import/AI/SearchAlgorithm.py
my_import/AI/TTT.py
my_import/AI/TransferLearning.py
my_import/AI/__init__.py
my_import/AI/auto_tqdm.py
my_import/AI/quick_call.py
my_import/AI/test.py
my_import/AI/GAN/ACGAN.py
my_import/AI/GAN/ClusterGAN.py
my_import/AI/GAN/ConditionalGAN.py
my_import/AI/GAN/GAN.py
my_import/AI/GAN/InfoGAN.py
my_import/AI/GAN/__init__.py
my_import/AI/GAN/baseGAN.py
my_import/AI/VAE/BetaVAE.py
my_import/AI/VAE/__init__.py
my_import/AI/VAE/baseVAE.py
my_import/AI/VAE/vae.py
my_import/Argument/Argument.py
my_import/Argument/__init__.py
my_import/Causal/__init__.py
my_import/Causal/causal_bound.py
my_import/Discord/Discord.py
my_import/Discord/__init__.py
my_import/Discord/config.py
my_import/files/__init__.py
my_import/files/file_processing.py
my_import/git_help/__init__.py
my_import/git_help/api.py
my_import/git_help/quick_pull.py
my_import/git_help/quick_push.py
my_import/git_help/utils.py
my_import/mnist_build/__init__.py
my_import/mnist_build/build.py
my_import/mprint/__init__.py
my_unique_import-0.3.17.dist-info/METADATA
my_unique_import-0.3.17.dist-info/WHEEL
my_unique_import-0.3.17.dist-info/entry_points.txt
my_unique_import-0.3.17.dist-info/top_level.txt
my_unique_import-0.3.17.dist-info/RECORD
