Metadata-Version: 2.1
Name: my-unique-import
Version: 0.3.17
Summary: A custom importer package
Home-page: https://pypi.org/project/my-unique-import/
Author: Jingyuan Chen
Author-email: jchensteve@gmail.com
License: MIT
Classifier: Programming Language :: Python :: 3
Classifier: License :: OSI Approved :: MIT License
Classifier: Operating System :: OS Independent
Requires-Python: >=3.9
Requires-Dist: tqdm ==4.66.4
